LICENSE
MANIFEST.in
README.rst
setup.py
tox.ini
ineedyou/__init__.py
ineedyou/exceptions.py
ineedyou.egg-info/PKG-INFO
ineedyou.egg-info/SOURCES.txt
ineedyou.egg-info/dependency_links.txt
ineedyou.egg-info/entry_points.txt
ineedyou.egg-info/requires.txt
ineedyou.egg-info/top_level.txt