Metadata-Version: 1.1
Name: ineedyou
Version: 0.0.2
Summary: I need you, but you need me too.
Home-page: https://bitbucket.org/johannestaas/ineedyou
Author: Johan Nestaas
Author-email: johannestaas@gmail.com
License: GPLv3
Keywords: circular
Platform: UNKNOWN
Classifier: Development Status :: 3 - Alpha
Classifier: Environment :: Console
Classifier: Environment :: X11 Applications :: Qt
Classifier: Environment :: MacOS X
Classifier: Environment :: Win32 (MS Windows)
Classifier: Operating System :: POSIX
Classifier: Operating System :: MacOS :: MacOS X
Classifier: Operating System :: Microsoft :: Windows
Classifier: Programming Language :: Python
